.bumpversion.cfg
.cookiecutterrc
.coveragerc
.editorconfig
.travis.yml
AUTHORS.rst
CHANGELOG.rst
CONTRIBUTING.rst
LICENSE
MANIFEST.in
README.rst
setup.cfg
setup.py
tox.ini
docs/Makefile
docs/cacheblob.handlers.rst
docs/cacheblob.rst
docs/conf.py
docs/index.rst
docs/make.bat
docs/_build/doctrees/cacheblob.doctree
docs/_build/doctrees/cacheblob.handlers.doctree
docs/_build/doctrees/environment.pickle
docs/_build/doctrees/index.doctree
docs/_build/html/.buildinfo
docs/_build/html/cacheblob.handlers.html
docs/_build/html/cacheblob.html
docs/_build/html/genindex.html
docs/_build/html/index.html
docs/_build/html/objects.inv
docs/_build/html/py-modindex.html
docs/_build/html/search.html
docs/_build/html/searchindex.js
docs/_build/html/_modules/index.html
docs/_build/html/_modules/cacheblob/cache.html
docs/_build/html/_modules/cacheblob/cli.html
docs/_build/html/_modules/cacheblob/db_wrapper.html
docs/_build/html/_modules/cacheblob/db_wrapper_table.html
docs/_build/html/_modules/cacheblob/item.html
docs/_build/html/_modules/cacheblob/handlers/gzip.html
docs/_build/html/_modules/cacheblob/handlers/handler.html
docs/_build/html/_modules/cacheblob/handlers/mongo.html
docs/_build/html/_modules/cacheblob/handlers/plaintext.html
docs/_build/html/_modules/cacheblob/handlers/sqlite.html
docs/_build/html/_sources/cacheblob.handlers.txt
docs/_build/html/_sources/cacheblob.txt
docs/_build/html/_sources/index.txt
docs/_build/html/_static/ajax-loader.gif
docs/_build/html/_static/alabaster.css
docs/_build/html/_static/basic.css
docs/_build/html/_static/comment-bright.png
docs/_build/html/_static/comment-close.png
docs/_build/html/_static/comment.png
docs/_build/html/_static/doctools.js
docs/_build/html/_static/down-pressed.png
docs/_build/html/_static/down.png
docs/_build/html/_static/file.png
docs/_build/html/_static/jquery-1.11.1.js
docs/_build/html/_static/jquery.js
docs/_build/html/_static/minus.png
docs/_build/html/_static/plus.png
docs/_build/html/_static/pygments.css
src/cacheblob.egg-info/PKG-INFO
src/cacheblob.egg-info/SOURCES.txt
src/cacheblob.egg-info/dependency_links.txt
src/cacheblob.egg-info/entry_points.txt
src/cacheblob.egg-info/not-zip-safe
src/cacheblob.egg-info/requires.txt
src/cacheblob.egg-info/top_level.txt
